simple_gl/__init__.py
simple_gl/branches.py
simple_gl/commits.py
simple_gl/gitlab_base.py
simple_gl/groups.py
simple_gl/hooks.py
simple_gl/merge_request.py
simple_gl/projects.py
simple_gl/utils.py
SimpleGL-0.1.5.9.dist-info/LICENSE
SimpleGL-0.1.5.9.dist-info/METADATA
SimpleGL-0.1.5.9.dist-info/WHEEL
SimpleGL-0.1.5.9.dist-info/top_level.txt
SimpleGL-0.1.5.9.dist-info/RECORD
