Metadata-Version: 2.1
Name: SimpleGL
Version: 0.1.5.9
Summary: UNKNOWN
Home-page: https://gitee.com/bbnoodle/simple_gl
Author: Maoxinteng
Author-email: 1214403402@qq.com
License: UNKNOWN
Platform: UNKNOWN
Classifier: Programming Language :: Python :: 3.6
Classifier: License :: OSI Approved :: MIT License
Classifier: Operating System :: OS Independent
Requires-Python: >=3.6
Requires-Dist: GITCodeAnalysis (==1.0.1)
